README
setup.cfg
setup.py
mockprocess/__init__.py
mockprocess/test_mockprocess.py
mockprocess.egg-info/PKG-INFO
mockprocess.egg-info/SOURCES.txt
mockprocess.egg-info/dependency_links.txt
mockprocess.egg-info/requires.txt
mockprocess.egg-info/top_level.txt
mockprocess.egg-info/zip-safe