Metadata-Version: 1.0
Name: mockprocess
Version: 0.2
Summary: Mocks for subprocess commands
Home-page: https://bitbucket.org/rw_grim/mockprocess
Author: Gary Kramlich
Author-email: grim@reaperworld.com
License: UNKNOWN
Platform: UNKNOWN
